README.rst
setup.py
alibabacloud_kms_kms20160120/__init__.py
alibabacloud_kms_kms20160120/client.py
alibabacloud_kms_kms20160120/models.py
alibabacloud_kms_kms20160120/transfer_client.py
alibabacloud_kms_kms20160120/handlers/__init__.py
alibabacloud_kms_kms20160120/handlers/advance_decrypt_transfer_handler.py
alibabacloud_kms_kms20160120/handlers/advance_encrypt_transfer_handler.py
alibabacloud_kms_kms20160120/handlers/advance_generate_data_key_transfer_handler.py
alibabacloud_kms_kms20160120/handlers/advance_generate_data_key_without_plaintext_transfer_handler.py
alibabacloud_kms_kms20160120/handlers/asymmetic_decrypt_transfer_handler.py
alibabacloud_kms_kms20160120/handlers/asymmetic_encrypt_transfer_handler.py
alibabacloud_kms_kms20160120/handlers/asymmetic_sign_transfer_handler.py
alibabacloud_kms_kms20160120/handlers/asymmetic_verify_transfer_handler.py
alibabacloud_kms_kms20160120/handlers/decrypt_transfer_handler.py
alibabacloud_kms_kms20160120/handlers/encrypt_transfer_handler.py
alibabacloud_kms_kms20160120/handlers/generate_data_key_transfer_handler.py
alibabacloud_kms_kms20160120/handlers/generate_data_key_without_plaintext_transfer_handler.py
alibabacloud_kms_kms20160120/handlers/get_public_key_transfer_handler.py
alibabacloud_kms_kms20160120/handlers/get_secret_value_transfer_handler.py
alibabacloud_kms_kms20160120/handlers/kms_transfer_handler.py
alibabacloud_kms_kms20160120/utils/__init__.py
alibabacloud_kms_kms20160120/utils/consts.py
alibabacloud_kms_kms20160120/utils/encryption_context_utils.py
alibabacloud_kms_kms20160120/utils/kms_error_code_transfer_utils.py
alibabacloud_kms_python_sdk.egg-info/PKG-INFO
alibabacloud_kms_python_sdk.egg-info/SOURCES.txt
alibabacloud_kms_python_sdk.egg-info/dependency_links.txt
alibabacloud_kms_python_sdk.egg-info/requires.txt
alibabacloud_kms_python_sdk.egg-info/top_level.txt